niveda_agents/__init__.py
niveda_agents/cli.py
niveda_agents/ai/__init__.py
niveda_agents/ai/azure_openai.py
niveda_agents/ai/groq.py
niveda_agents/ai/huggingface.py
niveda_agents/db/__init__.py
niveda_agents/db/mongo.py
niveda_agents/db/postgres.py
niveda_agents/utils/__init__.py
niveda_agents/utils/logger.py
niveda_agents-0.1.6.dist-info/LICENSE
niveda_agents-0.1.6.dist-info/METADATA
niveda_agents-0.1.6.dist-info/WHEEL
niveda_agents-0.1.6.dist-info/entry_points.txt
niveda_agents-0.1.6.dist-info/top_level.txt
niveda_agents-0.1.6.dist-info/RECORD
