Metadata-Version: 2.1
Name: niveda_agents
Version: 0.1.6
Summary: A powerful agentic framework for AI & database interactions.
Author: Sai Krishna Alle
Author-email: Sai Krishna Alle <saikrishnaalle1@gmail.com>
License: MIT
Requires-Python: >=3.8
License-File: LICENSE
Requires-Dist: psycopg2
Requires-Dist: pymongo
Requires-Dist: openai
Requires-Dist: azure-ai-textanalytics
Requires-Dist: transformers
Requires-Dist: fastapi
Requires-Dist: uvicorn
Requires-Dist: pytest
Requires-Dist: python-dotenv
Requires-Dist: groq
Requires-Dist: click
